automan/__init__.py
automan/api.py
automan/automation.py
automan/cluster_manager.py
automan/conda_cluster_manager.py
automan/edm_cluster_manager.py
automan/jobs.py
automan/utils.py
automan/tests/__init__.py
automan/tests/example.py
automan/tests/test_automation.py
automan/tests/test_cluster_manager.py
automan/tests/test_jobs.py
automan/tests/test_utils.py
automan-0.6.dist-info/LICENSE.txt
automan-0.6.dist-info/METADATA
automan-0.6.dist-info/WHEEL
automan-0.6.dist-info/top_level.txt
automan-0.6.dist-info/RECORD
